koala_serializer/__init__.py
koala_serializer/parser.py
koala_serializer/parser_core.py
koala_serializer/rule_parser.py
koala_serializer/code_generators/__init__.py
koala_serializer/code_generators/code_editor.py
koala_serializer/code_generators/cpp.py
koala_serializer/code_generators/cpp_core.py
koala_serializer/code_generators/cs.py
koala_serializer/code_generators/cs_core.py
koala_serializer/code_generators/java.py
koala_serializer/code_generators/java_core.py
koala_serializer/code_generators/python.py
koala_serializer/code_generators/python_core.py
koala_serializer-0.8.0.data/scripts/koalasc
koala_serializer-0.8.0.dist-info/DESCRIPTION.rst
koala_serializer-0.8.0.dist-info/METADATA
koala_serializer-0.8.0.dist-info/RECORD
koala_serializer-0.8.0.dist-info/WHEEL
koala_serializer-0.8.0.dist-info/metadata.json
koala_serializer-0.8.0.dist-info/top_level.txt
