Metadata-Version: 2.0
Name: koala-serializer
Version: 0.8.0
Summary: A tool designed for creating serializable objects among different programming languages
Home-page: https://github.com/koala-team/serializer
Author: Koala
Author-email: mdan.hagh@gmail.com
License: MIT
Keywords: serialize deserialize object compile binary
Platform: UNKNOWN
Classifier: Environment :: Console
Classifier: License :: OSI Approved :: MIT License
Classifier: Intended Audience :: Developers
Classifier: Operating System :: OS Independent
Classifier: Programming Language :: Python :: 2.7
Classifier: Programming Language :: Python :: 3.5
Classifier: Topic :: Utilities
Provides: koalasc
Requires-Dist: configparser (==3.5.0)
Requires-Dist: enum34 (==1.1.6)
